awconnection/__init__.py
awconnection/interface.py
awconnection/utility.py
awconnection-0.3.5.1.dist-info/LICENSE.txt
awconnection-0.3.5.1.dist-info/METADATA
awconnection-0.3.5.1.dist-info/WHEEL
awconnection-0.3.5.1.dist-info/top_level.txt
awconnection-0.3.5.1.dist-info/RECORD
