Metadata-Version: 2.1
Name: awconnection
Version: 0.3.5.1
Summary: An interface between Python and AutonoWar
Home-page: https://github.com/griffinteller/awconnection
Author: Griffin Teller
Author-email: griffinteller@gmail.com
License: MIT
Platform: UNKNOWN
Classifier: Development Status :: 2 - Pre-Alpha
Classifier: License :: OSI Approved :: MIT License
Classifier: Programming Language :: Python :: 3
Classifier: Topic :: Software Development :: Libraries
Classifier: Topic :: Software Development :: Libraries :: Python Modules
Classifier: Intended Audience :: Education
Requires-Python: >=3.6
Requires-Dist: pywin32 (==227) ; platform_system == "Windows"
